pyivia/__init__.py
pyivia/__main__.py
pyivia/factory.py
pyivia/core/__init__.py
pyivia/core/advancedaccesscontrol.py
pyivia/core/analysisdiagnostics.py
pyivia/core/federationsettings.py
pyivia/core/systemsettings.py
pyivia/core/websettings.py
pyivia/core/access/__init__.py
pyivia/core/access/accesscontrol.py
pyivia/core/access/advancedconfig.py
pyivia/core/access/apiprotection.py
pyivia/core/access/attributes.py
pyivia/core/access/authentication.py
pyivia/core/access/fido2config.py
pyivia/core/access/fido2registrations.py
pyivia/core/access/mappingrules.py
pyivia/core/access/mmfaconfig.py
pyivia/core/access/pip.py
pyivia/core/access/pushnotification.py
pyivia/core/access/riskprofiles.py
pyivia/core/access/runtimeparameters.py
pyivia/core/access/scimconfig.py
pyivia/core/access/serverconnections.py
pyivia/core/access/templatefiles.py
pyivia/core/access/userregistry.py
pyivia/core/analysis/__init__.py
pyivia/core/analysis/applicationlog.py
pyivia/core/analysis/remotesyslog.py
pyivia/core/federation/__init__.py
pyivia/core/federation/accesspolicy.py
pyivia/core/federation/aliasservice.py
pyivia/core/federation/attributesources.py
pyivia/core/federation/federations.py
pyivia/core/federation/pointofcontact.py
pyivia/core/federation/securitytokenservice.py
pyivia/core/system/__init__.py
pyivia/core/system/adminsettings.py
pyivia/core/system/advancedtuning.py
pyivia/core/system/clicommands.py
pyivia/core/system/cluster.py
pyivia/core/system/configuration.py
pyivia/core/system/containermanagement.py
pyivia/core/system/datetime.py
pyivia/core/system/dns.py
pyivia/core/system/docker.py
pyivia/core/system/dsc.py
pyivia/core/system/extensions.py
pyivia/core/system/filedownloads.py
pyivia/core/system/fips.py
pyivia/core/system/firststeps.py
pyivia/core/system/fixpacks.py
pyivia/core/system/general.py
pyivia/core/system/hostsfile.py
pyivia/core/system/interfaces.py
pyivia/core/system/licensing.py
pyivia/core/system/managementauthentication.py
pyivia-0.2.37.dist-info/licenses/AUTHORS.md
pyivia-0.2.37.dist-info/licenses/LICENSE.txt
pyivia-0.2.37.dist-info/METADATA
pyivia-0.2.37.dist-info/WHEEL
pyivia-0.2.37.dist-info/top_level.txt
pyivia-0.2.37.dist-info/RECORD
