Metadata-Version: 2.4
Name: pyivia
Version: 0.2.37
Summary: Python API for IBM Verify Identity Access
Home-page: https://github.com/lachlan-ibm/pyivia
Author: Lachlan Gleeson
Author-email: lgleeson@au1.ibm.com
License: MIT
Project-URL: Homepage, https://github.com/lachlan-ibm/pyivia
Project-URL: Documentation, https://lachlan-ibm.github.io/pyivia
Project-URL: Source, https://github.com/lachlan-ibm/pyivia
Project-URL: Tracker, https://github.com/lachlan-ibm/pyivia/issues
License-File: LICENSE.txt
License-File: AUTHORS.md
Requires-Dist: requests>=2.23.0
Dynamic: author
Dynamic: author-email
Dynamic: description
Dynamic: description-content-type
Dynamic: home-page
Dynamic: license
Dynamic: license-file
Dynamic: project-url
Dynamic: requires-dist
Dynamic: summary
